yamlisp/__init__.py
yamlisp/__version__.py
yamlisp/eval.py
yamlisp/functions.py
yamlisp/path.py
yamlisp/yaml.py
yamlisp-0.0.0.dist-info/DESCRIPTION.rst
yamlisp-0.0.0.dist-info/METADATA
yamlisp-0.0.0.dist-info/RECORD
yamlisp-0.0.0.dist-info/WHEEL
yamlisp-0.0.0.dist-info/entry_points.txt
yamlisp-0.0.0.dist-info/metadata.json
yamlisp-0.0.0.dist-info/top_level.txt
