Metadata-Version: 2.0
Name: yamlisp
Version: 0.0.0
Summary: Compile configuration files out of yaml files with additional syntax and lisp-like macros.
